co2mpas/__init__.py
co2mpas/_version.py
co2mpas/defaults.py
co2mpas/utils.py
co2mpas/cli/__init__.py
co2mpas/cli/sync.py
co2mpas/core/__init__.py
co2mpas/core/report.py
co2mpas/core/load/__init__.py
co2mpas/core/load/excel.py
co2mpas/core/load/schema.py
co2mpas/core/load/validate/__init__.py
co2mpas/core/load/validate/hard.py
co2mpas/core/model/__init__.py
co2mpas/core/model/physical/__init__.py
co2mpas/core/model/physical/after_treat.py
co2mpas/core/model/physical/co2.py
co2mpas/core/model/physical/final_drive.py
co2mpas/core/model/physical/vehicle.py
co2mpas/core/model/physical/wheels.py
co2mpas/core/model/physical/clutch_tc/__init__.py
co2mpas/core/model/physical/clutch_tc/clutch.py
co2mpas/core/model/physical/clutch_tc/torque_converter.py
co2mpas/core/model/physical/control/__init__.py
co2mpas/core/model/physical/control/conventional.py
co2mpas/core/model/physical/control/hybrid.py
co2mpas/core/model/physical/cycle/NEDC.py
co2mpas/core/model/physical/cycle/__init__.py
co2mpas/core/model/physical/cycle/WLTP/__init__.py
co2mpas/core/model/physical/cycle/WLTP/gears.py
co2mpas/core/model/physical/cycle/WLTP/vel.py
co2mpas/core/model/physical/electrics/__init__.py
co2mpas/core/model/physical/electrics/batteries/__init__.py
co2mpas/core/model/physical/electrics/batteries/dcdc.py
co2mpas/core/model/physical/electrics/batteries/drive.py
co2mpas/core/model/physical/electrics/batteries/service/__init__.py
co2mpas/core/model/physical/electrics/batteries/service/status.py
co2mpas/core/model/physical/electrics/motors/__init__.py
co2mpas/core/model/physical/electrics/motors/p0.py
co2mpas/core/model/physical/electrics/motors/p1.py
co2mpas/core/model/physical/electrics/motors/p2.py
co2mpas/core/model/physical/electrics/motors/p3.py
co2mpas/core/model/physical/electrics/motors/p4.py
co2mpas/core/model/physical/electrics/motors/planet.py
co2mpas/core/model/physical/electrics/motors/starter.py
co2mpas/core/model/physical/electrics/motors/alternator/__init__.py
co2mpas-4.3.6.dist-info/LICENSE
co2mpas-4.3.6.dist-info/METADATA
co2mpas-4.3.6.dist-info/WHEEL
co2mpas-4.3.6.dist-info/entry_points.txt
co2mpas-4.3.6.dist-info/top_level.txt
co2mpas-4.3.6.dist-info/zip-safe
co2mpas-4.3.6.dist-info/RECORD
