Metadata-Version: 2.2
Name: co2mpas
Version: 4.3.6
Summary: The Type-Approving vehicle simulator predicting NEDC CO2 emissions from WLTP
Home-page: https://github.com/JRCSTU/co2mpas-ta
Download-URL: https://github.com/JRCSTU/co2mpas-ta/tarball/v4.3.6
Author: CO2MPAS-Team
Author-email: JRC-CO2MPAS@ec.europa.eu
License: EUPL 1.1+
Project-URL: Documentation, http://co2mpas.readthedocs.io
Project-URL: Issue tracker, https://github.com/JRCSTU/co2mpas-ta/issues
Keywords: CO2,fuel-consumption,WLTP,NEDC,vehicle,automotive,EU,JRC,IET,STU,correlation,back-translation,policy,monitoring,M1,N1,simulator,engineering,scientific
Platform: any
Classifier: Programming Language :: Python
Classifier: Programming Language :: Python :: 3
Classifier: Programming Language :: Python :: 3.6
Classifier: Programming Language :: Python :: 3.7
Classifier: Programming Language :: Python :: Implementation :: CPython
Classifier: Development Status :: 4 - Beta
Classifier: Natural Language :: English
Classifier: Intended Audience :: Developers
Classifier: Intended Audience :: Science/Research
Classifier: Intended Audience :: Manufacturing
Classifier: Environment :: Console
Classifier: License :: OSI Approved :: European Union Public Licence 1.1 (EUPL 1.1)
Classifier: Natural Language :: English
Classifier: Operating System :: MacOS :: MacOS X
Classifier: Operating System :: Microsoft :: Windows
Classifier: Operating System :: POSIX
Classifier: Operating System :: Unix
Classifier: Operating System :: OS Independent
Classifier: Topic :: Scientific/Engineering
Classifier: Topic :: Scientific/Engineering :: Information Analysis
Obsoletes: co2mpas (< 4.0)
Requires-Python: >=3.5
License-File: LICENSE
Requires-Dist: PyYAML
Requires-Dist: schedula>=0.3.2
Requires-Dist: tqdm
Requires-Dist: scikit-learn
Requires-Dist: regex
Requires-Dist: lmfit>=0.9.7
Requires-Dist: numpy
Requires-Dist: schema
Requires-Dist: scipy
Requires-Dist: wltp
Requires-Dist: wltp-jrshift
Requires-Dist: xgboost>=0.90
Requires-Dist: statsmodels
Requires-Dist: syncing>=1.0.4
Provides-Extra: cli
Requires-Dist: click; extra == "cli"
Requires-Dist: click-log; extra == "cli"
Provides-Extra: sync
Requires-Dist: syncing>=1.0.4; extra == "sync"
Requires-Dist: pandas>=0.21.0; extra == "sync"
Provides-Extra: plot
Requires-Dist: flask; extra == "plot"
Requires-Dist: regex; extra == "plot"
Requires-Dist: graphviz; extra == "plot"
Requires-Dist: Pygments; extra == "plot"
Requires-Dist: lxml; extra == "plot"
Requires-Dist: beautifulsoup4; extra == "plot"
Requires-Dist: jinja2; extra == "plot"
Requires-Dist: docutils; extra == "plot"
Requires-Dist: plotly; extra == "plot"
Provides-Extra: io
Requires-Dist: pandas>=0.21.0; extra == "io"
Requires-Dist: dill; extra == "io"
Requires-Dist: regex; extra == "io"
Requires-Dist: xlref; extra == "io"
Requires-Dist: xlrd; extra == "io"
Requires-Dist: asteval; extra == "io"
Provides-Extra: dice
Requires-Dist: co2mpas_dice>=4.0.5; extra == "dice"
Requires-Dist: pandas>=0.21.0; extra == "dice"
Requires-Dist: dill; extra == "dice"
Requires-Dist: regex; extra == "dice"
Requires-Dist: xlref; extra == "dice"
Requires-Dist: xlrd; extra == "dice"
Requires-Dist: asteval; extra == "dice"
Provides-Extra: all
Requires-Dist: pandas>=0.21.0; extra == "all"
Requires-Dist: beautifulsoup4; extra == "all"
Requires-Dist: plotly; extra == "all"
Requires-Dist: syncing>=1.0.4; extra == "all"
Requires-Dist: click-log; extra == "all"
Requires-Dist: docutils; extra == "all"
Requires-Dist: asteval; extra == "all"
Requires-Dist: graphviz; extra == "all"
Requires-Dist: Pygments; extra == "all"
Requires-Dist: co2mpas_dice>=4.0.5; extra == "all"
Requires-Dist: click; extra == "all"
Requires-Dist: xlrd; extra == "all"
Requires-Dist: flask; extra == "all"
Requires-Dist: regex; extra == "all"
Requires-Dist: lxml; extra == "all"
Requires-Dist: xlref; extra == "all"
Requires-Dist: jinja2; extra == "all"
Requires-Dist: dill; extra == "all"
Provides-Extra: dev
Requires-Dist: pandas>=0.21.0; extra == "dev"
Requires-Dist: beautifulsoup4; extra == "dev"
Requires-Dist: plotly; extra == "dev"
Requires-Dist: syncing>=1.0.4; extra == "dev"
Requires-Dist: click-log; extra == "dev"
Requires-Dist: docutils; extra == "dev"
Requires-Dist: asteval; extra == "dev"
Requires-Dist: graphviz; extra == "dev"
Requires-Dist: Pygments; extra == "dev"
Requires-Dist: co2mpas_dice>=4.0.5; extra == "dev"
Requires-Dist: click; extra == "dev"
Requires-Dist: xlrd; extra == "dev"
Requires-Dist: flask; extra == "dev"
Requires-Dist: regex; extra == "dev"
Requires-Dist: lxml; extra == "dev"
Requires-Dist: xlref; extra == "dev"
Requires-Dist: jinja2; extra == "dev"
Requires-Dist: dill; extra == "dev"
Requires-Dist: wheel; extra == "dev"
Requires-Dist: sphinx; extra == "dev"
Requires-Dist: gitchangelog; extra == "dev"
Requires-Dist: mako; extra == "dev"
Requires-Dist: sphinx_rtd_theme; extra == "dev"
Requires-Dist: setuptools>=36.0.1; extra == "dev"
Requires-Dist: sphinxcontrib-restbuilder; extra == "dev"
Requires-Dist: nose; extra == "dev"
Requires-Dist: coveralls; extra == "dev"
Requires-Dist: ddt; extra == "dev"
Requires-Dist: sphinx-click; extra == "dev"
Dynamic: author
Dynamic: author-email
Dynamic: classifier
Dynamic: download-url
Dynamic: home-page
Dynamic: keywords
Dynamic: license
Dynamic: obsoletes
Dynamic: platform
Dynamic: project-url
Dynamic: provides-extra
Dynamic: requires-dist
Dynamic: requires-python
Dynamic: summary
